gcp_cli/__init__.py
gcp_cli/ai_generator.py
gcp_cli/cli.py
gcp_cli/config.py
gcp_cli/credentials.py
gcp_cli/executor.py
gcp_cli/utils.py
gcp_cli_ai-0.2.0.dist-info/licenses/LICENSE
gcp_cli_ai-0.2.0.dist-info/METADATA
gcp_cli_ai-0.2.0.dist-info/WHEEL
gcp_cli_ai-0.2.0.dist-info/entry_points.txt
gcp_cli_ai-0.2.0.dist-info/top_level.txt
gcp_cli_ai-0.2.0.dist-info/RECORD
