Metadata-Version: 2.4
Name: gcp-cli-ai
Version: 0.2.0
Summary: AI-powered CLI for executing GCP commands using natural language
Home-page: https://github.com/Cgraj07/gcp-cli
Author: Govind
Author-email: Govind <gopichinnaraj123@gmail.com>
Maintainer-email: Govind <gopichinnaraj123@gmail.com>
License: MIT
Project-URL: Homepage, https://github.com/Cgraj07/gcp-cli
Project-URL: Repository, https://github.com/Cgraj07/gcp-cli
Project-URL: Issues, https://github.com/Cgraj07/gcp-cli/issues
Project-URL: Documentation, https://github.com/Cgraj07/gcp-cli#readme
Keywords: gcp,google-cloud,cli,ai,gemini,vertex-ai,automation,cloud,devops
Classifier: Development Status :: 3 - Alpha
Classifier: Intended Audience :: Developers
Classifier: Topic :: Software Development :: Libraries :: Python Modules
Classifier: Topic :: System :: Systems Administration
Classifier: License :: OSI Approved :: MIT License
Classifier: Programming Language :: Python :: 3
Classifier: Programming Language :: Python :: 3.8
Classifier: Programming Language :: Python :: 3.9
Classifier: Programming Language :: Python :: 3.10
Classifier: Programming Language :: Python :: 3.11
Classifier: Programming Language :: Python :: 3.12
Requires-Python: >=3.8
License-File: LICENSE
Requires-Dist: google-cloud-aiplatform>=1.38.0
Requires-Dist: click>=8.1.0
Requires-Dist: PyYAML>=6.0
Requires-Dist: rich>=13.0.0
Requires-Dist: google-auth>=2.23.0
Requires-Dist: google-cloud-storage>=2.10.0
Provides-Extra: dev
Requires-Dist: pytest>=7.0; extra == "dev"
Requires-Dist: pytest-cov>=4.0; extra == "dev"
Requires-Dist: black>=23.0; extra == "dev"
Requires-Dist: flake8>=6.0; extra == "dev"
Requires-Dist: mypy>=1.0; extra == "dev"
Dynamic: author
Dynamic: home-page
Dynamic: license-file
Dynamic: requires-python
